natural_questions/__init__.py
natural_questions/eval_utils.py
natural_questions/eval_utils_test.py
natural_questions/make_test_data.py
natural_questions/nq_browser.py
natural_questions/nq_eval.py
natural_questions/nq_eval_test.py
natural_questions/simplify_nq_data.py
natural_questions/text_utils.py
natural_questions-1.0.6.dist-info/LICENSE
natural_questions-1.0.6.dist-info/METADATA
natural_questions-1.0.6.dist-info/WHEEL
natural_questions-1.0.6.dist-info/top_level.txt
natural_questions-1.0.6.dist-info/RECORD
